gw2api/__init__.py
gw2api/objects/__init__.py
gw2api/objects/base_object.py
gw2api/objects/api_version_1/__init__.py
gw2api/objects/api_version_2/__init__.py
GuildWars2_API_Client-0.7.0.dist-info/METADATA
GuildWars2_API_Client-0.7.0.dist-info/WHEEL
GuildWars2_API_Client-0.7.0.dist-info/top_level.txt
GuildWars2_API_Client-0.7.0.dist-info/RECORD
