Metadata-Version: 2.1
Name: GuildWars2-API-Client
Version: 0.7.0
Summary: Library that interfaces with the Guild Wars 2 API that supports v1 and v2
Author-email: juxhin <juxhin@digital-horror.com>
License: MIT License
Project-URL: Home, https://github.com/JuxhinDB/gw2-api-interface
Keywords: guildwars,api,gw2
Requires-Dist: requests
Provides-Extra: dev
Requires-Dist: ruff; extra == "dev"
